README.rst
setup.py
sippycup/__init__.py
sippycup.egg-info/PKG-INFO
sippycup.egg-info/SOURCES.txt
sippycup.egg-info/dependency_links.txt
sippycup.egg-info/requires.txt
sippycup.egg-info/top_level.txt