Metadata-Version: 1.1
Name: sippycup
Version: 0.5.4
Summary: An adaptor for serving WSGI applications using AWS Lambda and API Gateway
Home-page: https://github.com/realsalmon/sippycup
Author: Ben Jones
Author-email: ben@fogbutter.com
License: MIT
Keywords: aws lambda api serverless wsgi
Platform: UNKNOWN
Classifier: Development Status :: 4 - Beta
Classifier: Intended Audience :: Developers
Classifier: License :: OSI Approved :: MIT License
Classifier: Programming Language :: Python :: 2
Classifier: Programming Language :: Python :: 2.7
Classifier: Programming Language :: Python :: 3
Classifier: Programming Language :: Python :: 3.6
Classifier: Operating System :: OS Independent
Classifier: Topic :: Internet :: WWW/HTTP
Classifier: Topic :: Software Development
